superagentx_handlers/__init__.py
superagentx_handlers/asana_handler.py
superagentx_handlers/atlassian/__init__.py
superagentx_handlers/atlassian/confluence.py
superagentx_handlers/atlassian/exceptions.py
superagentx_handlers/atlassian/jira.py
superagentx_handlers/aws/__init__.py
superagentx_handlers/aws/api_gateway.py
superagentx_handlers/aws/cloudfront.py
superagentx_handlers/aws/cloudwatch.py
superagentx_handlers/aws/cognito.py
superagentx_handlers/aws/ec2.py
superagentx_handlers/aws/ecs.py
superagentx_handlers/aws/elasticache.py
superagentx_handlers/aws/elb.py
superagentx_handlers/aws/helper.py
superagentx_handlers/aws/iam.py
superagentx_handlers/aws/rds.py
superagentx_handlers/aws/s3.py
superagentx_handlers/aws/security_groups.py
superagentx_handlers/aws/serverless.py
superagentx_handlers/azure/__init__.py
superagentx_handlers/azure/application_gateway.py
superagentx_handlers/azure/cloud_functions.py
superagentx_handlers/azure/iam.py
superagentx_handlers/azure/loadbalancer.py
superagentx_handlers/azure/nsg.py
superagentx_handlers/azure/storage.py
superagentx_handlers/azure/vm.py
superagentx_handlers/crm/__init__.py
superagentx_handlers/crm/hubspot_crm.py
superagentx_handlers/csv_cli.py
superagentx_handlers/cybersecurity/__init__.py
superagentx_handlers/cybersecurity/snyk.py
superagentx_handlers/datadog/__init__.py
superagentx_handlers/datadog/incidents.py
superagentx_handlers/ecommerce/__init__.py
superagentx_handlers/ecommerce/amazon.py
superagentx_handlers/ecommerce/best_buy.py
superagentx_handlers/ecommerce/fake_amazon.py
superagentx_handlers/ecommerce/fake_flipkart.py
superagentx_handlers/ecommerce/fake_product.py
superagentx_handlers/ecommerce/flipkart.py
superagentx_handlers/ecommerce/walmart.py
superagentx_handlers/extract/__init__.py
superagentx_handlers/extract/ai.py
superagentx_handlers/gcp/__init__.py
superagentx_handlers/gcp/api_gateway.py
superagentx_handlers/gcp/calender.py
superagentx_handlers/gcp/cloud_run.py
superagentx_handlers/gcp/compute.py
superagentx_handlers-0.1.7.dist-info/METADATA
superagentx_handlers-0.1.7.dist-info/WHEEL
superagentx_handlers-0.1.7.dist-info/licenses/LICENSE
superagentx_handlers-0.1.7.dist-info/RECORD
