Metadata-Version: 2.4
Name: superagentx-handlers
Version: 0.1.7
Summary: 
License: MIT
License-File: LICENSE
Keywords: superagentX,AGI,Agentic AI,ASI,superagentx,agent,LLM
Author: SuperAgentX AI
Author-email: support@superagentx.ai
Maintainer: SuperAgentX AI
Maintainer-email: support@superagentx.ai
Requires-Python: >=3.12,<=3.13
Classifier: License :: OSI Approved :: MIT License
Classifier: Programming Language :: Python :: 3
Classifier: Programming Language :: Python :: 3.12
Classifier: Programming Language :: Python :: 3.13
Requires-Dist: aiohttp (>=3.10.10,<4.0.0)
Requires-Dist: aiomysql (>=0.2.0,<0.3.0)
Requires-Dist: aioodbc (>=0.5.0,<0.6.0)
Requires-Dist: atlassian-python-api (>=3.41.16,<4.0.0)
Requires-Dist: azure-identity (>=1.23.0,<2.0.0)
Requires-Dist: azure-mgmt-apimanagement (>=5.0.0,<6.0.0)
Requires-Dist: azure-mgmt-authorization (>=4.0.0,<5.0.0)
Requires-Dist: azure-mgmt-compute (==34.1.0)
Requires-Dist: azure-mgmt-network (>=29.0.0,<30.0.0)
Requires-Dist: azure-mgmt-resource (>=24.0.0,<25.0.0)
Requires-Dist: azure-mgmt-storage (>=23.0.1,<24.0.0)
Requires-Dist: azure-mgmt-web (>=9.0.0,<10.0.0)
Requires-Dist: azure-storage-blob (>=12.25.1,<13.0.0)
Requires-Dist: boto3 (>=1.38.42,<2.0.0)
Requires-Dist: crawl4ai (>=0.3.731,<0.4.0)
Requires-Dist: datadog-api-client[async] (>=2.39.0,<3.0.0)
Requires-Dist: google-api-python-client (>=2.149.0,<3.0.0)
Requires-Dist: google-auth-oauthlib (>=1.2.1,<2.0.0)
Requires-Dist: google-cloud-api-gateway (>=1.12.2,<2.0.0)
Requires-Dist: google-cloud-compute (>=1.31.0,<2.0.0)
Requires-Dist: google-cloud-iam (>=2.19.1,<3.0.0)
Requires-Dist: google-cloud-resource-manager (>=1.14.2,<2.0.0)
Requires-Dist: google-cloud-run (>=0.10.18,<0.11.0)
Requires-Dist: google-cloud-storage (>=3.2.0,<4.0.0)
Requires-Dist: hubspot-api-client (>=10.0.0,<11.0.0)
Requires-Dist: jira (>=3.8.0,<4.0.0)
Requires-Dist: lxml-html-clean (>=0.4.1,<0.5.0)
Requires-Dist: msgraph-sdk (>=1.34.0,<2.0.0)
Requires-Dist: openai (>=1.52.0,<2.0.0)
Requires-Dist: oracledb (>=2.4.1,<3.0.0)
Requires-Dist: psycopg2-binary (>=2.9.10,<3.0.0)
Requires-Dist: pymssql (>=2.3.1,<3.0.0)
Requires-Dist: pypdf (>=5.0.1,<6.0.0)
Requires-Dist: pyshorteners (>=1.0.1,<2.0.0)
Requires-Dist: pysnc (==1.1.10)
Requires-Dist: python-gitlab (==6.1.0)
Requires-Dist: requests-html (>=0.10.0,<0.11.0)
Requires-Dist: slack-sdk (>=3.35.0,<4.0.0)
Requires-Dist: sqlalchemy[asyncio] (>=2.0.36,<3.0.0)
Requires-Dist: tweepy[async] (>=4.14.0,<5.0.0)
Requires-Dist: wikipedia-api (>=0.7.1,<0.8.0)
Project-URL: Documentation, https://docs.superagentx.ai/
Project-URL: Homepage, https://www.superagentx.ai/
Project-URL: Repository, https://github.com/superagentxai/superagentx
